pycharter/__init__.py
pycharter/cli.py
pycharter/config.py
pycharter/py.typed
pycharter/api/README.md
pycharter/api/__init__.py
pycharter/api/main.py
pycharter/api/utils.py
pycharter/api/dependencies/__init__.py
pycharter/api/dependencies/database.py
pycharter/api/dependencies/store.py
pycharter/api/models/__init__.py
pycharter/api/models/contracts.py
pycharter/api/models/docs.py
pycharter/api/models/evolution.py
pycharter/api/models/metadata.py
pycharter/api/models/metadata_entities.py
pycharter/api/models/quality.py
pycharter/api/models/schemas.py
pycharter/api/models/tracking.py
pycharter/api/models/validation.py
pycharter/api/routes/__init__.py
pycharter/api/routes/v1/__init__.py
pycharter/api/routes/v1/contracts.py
pycharter/api/routes/v1/docs.py
pycharter/api/routes/v1/evolution.py
pycharter/api/routes/v1/metadata.py
pycharter/api/routes/v1/quality.py
pycharter/api/routes/v1/schemas.py
pycharter/api/routes/v1/settings.py
pycharter/api/routes/v1/templates.py
pycharter/api/routes/v1/tracking.py
pycharter/api/routes/v1/validation.py
pycharter/api/routes/v1/validation_jobs.py
pycharter/contract_builder/__init__.py
pycharter/contract_builder/builder.py
pycharter/contract_parser/__init__.py
pycharter/contract_parser/parser.py
pycharter/data/__init__.py
pycharter/data/templates/contract/README.md
pycharter/data/templates/contract/template_coercion_rules.yaml
pycharter/data/templates/contract/template_contract.yaml
pycharter/data/templates/contract/template_metadata.yaml
pycharter/data/templates/contract/template_schema.yaml
pycharter/data/templates/contract/template_validation_rules.yaml
pycharter/data/templates/etl/README.md
pycharter/data/templates/etl/extract_cloud_azure.yaml
pycharter/data/templates/etl/extract_cloud_gcs.yaml
pycharter/data/templates/etl/extract_cloud_s3.yaml
pycharter/data/templates/etl/extract_database.yaml
pycharter/data/templates/etl/extract_database_ssh.yaml
pycharter/data/templates/etl/extract_file_csv.yaml
pycharter-0.0.25.dist-info/licenses/LICENSE
pycharter-0.0.25.dist-info/METADATA
pycharter-0.0.25.dist-info/WHEEL
pycharter-0.0.25.dist-info/entry_points.txt
pycharter-0.0.25.dist-info/top_level.txt
pycharter-0.0.25.dist-info/RECORD
