Metadata-Version: 2.4
Name: pycharter
Version: 0.0.25
Summary: A Python package for data contract management with five core services: contract parsing, metadata storage, Pydantic generation, JSON Schema conversion, and runtime validation
Author-email: semantic developers <na@example.com>
License-Expression: MIT
Project-URL: Homepage, https://github.com/auscheng/pycharter
Project-URL: Documentation, https://github.com/auscheng/pycharter#readme
Project-URL: Repository, https://github.com/auscheng/pycharter
Project-URL: Issues, https://github.com/auscheng/pycharter/issues
Keywords: semantic,python,pydantic,contract,validation,schema
Classifier: Development Status :: 3 - Alpha
Classifier: Intended Audience :: Developers
Classifier: Programming Language :: Python :: 3
Classifier: Programming Language :: Python :: 3.10
Classifier: Programming Language :: Python :: 3.11
Classifier: Programming Language :: Python :: 3.12
Requires-Python: >=3.10
License-File: LICENSE
Requires-Dist: pydantic>=2.0.0
Requires-Dist: jsonschema>=4.0.0
Requires-Dist: pandas>=2.0.0
Requires-Dist: numpy>=1.24.0
Requires-Dist: pyyaml>=6.0.0
Requires-Dist: sqlalchemy>=2.0.0
Requires-Dist: alembic>=1.13.0
Requires-Dist: jsonata-python>=0.6.0
Provides-Extra: dev
Requires-Dist: pytest>=7.0.0; extra == "dev"
Requires-Dist: pytest-cov>=4.0.0; extra == "dev"
Requires-Dist: black>=23.0.0; extra == "dev"
Requires-Dist: isort>=5.12.0; extra == "dev"
Requires-Dist: mypy>=1.0.0; extra == "dev"
Requires-Dist: build>=0.10.0; extra == "dev"
Requires-Dist: twine>=4.0.0; extra == "dev"
Requires-Dist: jupyterlab>=4.0.0; extra == "dev"
Requires-Dist: ipykernel>=6.0.0; extra == "dev"
Requires-Dist: psycopg2-binary>=2.9.0; extra == "dev"
Requires-Dist: pymongo>=4.0.0; extra == "dev"
Requires-Dist: boto3>=1.26.0; extra == "dev"
Provides-Extra: api
Requires-Dist: fastapi>=0.104.0; extra == "api"
Requires-Dist: uvicorn[standard]>=0.24.0; extra == "api"
Requires-Dist: pydantic-settings>=2.0.0; extra == "api"
Requires-Dist: python-multipart>=0.0.6; extra == "api"
Provides-Extra: ui
Requires-Dist: fastapi>=0.104.0; extra == "ui"
Requires-Dist: uvicorn[standard]>=0.24.0; extra == "ui"
Requires-Dist: httpx>=0.24.0; extra == "ui"
Requires-Dist: aiofiles>=23.0.0; extra == "ui"
Provides-Extra: worker
Requires-Dist: pyspark>=3.5.0; extra == "worker"
Requires-Dist: redis>=5.0.0; extra == "worker"
Provides-Extra: etl
Requires-Dist: sshtunnel>=0.4.0; extra == "etl"
Requires-Dist: boto3>=1.26.0; extra == "etl"
Requires-Dist: google-cloud-storage>=2.0.0; extra == "etl"
Requires-Dist: azure-storage-blob>=12.0.0; extra == "etl"
Requires-Dist: openpyxl>=3.0.0; extra == "etl"
Requires-Dist: lxml>=4.9.0; extra == "etl"
Dynamic: license-file
